sam45/__init__.py
sam45/dtypes.py
sam45/dtypes.toml
sam45/py.typed
sam45/read.py
sam45-1.0.1.dist-info/METADATA
sam45-1.0.1.dist-info/WHEEL
sam45-1.0.1.dist-info/licenses/LICENSE
sam45-1.0.1.dist-info/RECORD
