Metadata-Version: 2.4
Name: sam45
Version: 1.0.1
Summary: NRO/SAM45 log reader
Project-URL: homepage, https://astropenguin.github.io/sam45
Project-URL: repository, https://github.com/astropenguin/sam45
Author-email: Akio Taniguchi <a-taniguchi@mail.kitami-it.ac.jp>
License: MIT License
License-File: LICENSE
Keywords: astronomy,nro,python,radio-astronomy,sam45
Classifier: License :: OSI Approved :: MIT License
Classifier: Programming Language :: Python :: 3
Classifier: Programming Language :: Python :: 3.10
Classifier: Programming Language :: Python :: 3.11
Classifier: Programming Language :: Python :: 3.12
Classifier: Programming Language :: Python :: 3.13
Classifier: Programming Language :: Python :: 3.14
Requires-Python: <3.15,>=3.10
Requires-Dist: numpy<3,>=2
Requires-Dist: tomli<3,>=2
